midastrader/__init__.py
midastrader/cli.py
midastrader/config.py
midastrader/engine.py
midastrader/message_bus.py
midastrader/core/__init__.py
midastrader/core/engine.py
midastrader/core/adapters/__init__.py
midastrader/core/adapters/base.py
midastrader/core/adapters/base_strategy.py
midastrader/core/adapters/database_updater.py
midastrader/core/adapters/order_book.py
midastrader/core/adapters/order_manager.py
midastrader/core/adapters/performance/__init__.py
midastrader/core/adapters/performance/base.py
midastrader/core/adapters/performance/managers.py
midastrader/core/adapters/portfolio/__init__.py
midastrader/core/adapters/portfolio/base.py
midastrader/core/adapters/portfolio/managers.py
midastrader/core/adapters/risk/__init__.py
midastrader/core/adapters/risk/base_risk_model.py
midastrader/core/adapters/risk/risk_handler.py
midastrader/data/__init__.py
midastrader/data/engine.py
midastrader/data/adaptors/__init__.py
midastrader/data/adaptors/base.py
midastrader/data/adaptors/historical/__init__.py
midastrader/data/adaptors/historical/data_client.py
midastrader/data/adaptors/ib/__init__.py
midastrader/data/adaptors/ib/client.py
midastrader/data/adaptors/ib/wrapper.py
midastrader/execution/__init__.py
midastrader/execution/engine.py
midastrader/execution/adaptors/__init__.py
midastrader/execution/adaptors/base.py
midastrader/execution/adaptors/dummy/__init__.py
midastrader/execution/adaptors/dummy/broker_client.py
midastrader/execution/adaptors/dummy/dummy_broker.py
midastrader/execution/adaptors/ib/__init__.py
midastrader/execution/adaptors/ib/client.py
midastrader/execution/adaptors/ib/wrapper.py
midastrader/structs/__init__.py
midastrader/structs/account.py
midastrader/structs/active_orders.py
midastrader/structs/orders.py
midastrader/structs/positions.py
midastrader/structs/signal.py
midastrader/structs/symbol.py
midastrader/structs/trade.py
midastrader/structs/events/__init__.py
midastrader/structs/events/base.py
midastrader/structs/events/eod_event.py
midastrader-1.0.30.dist-info/licenses/LICENSE
midastrader-1.0.30.dist-info/METADATA
midastrader-1.0.30.dist-info/WHEEL
midastrader-1.0.30.dist-info/top_level.txt
midastrader-1.0.30.dist-info/RECORD
